uarray-0.9.3.dist-info/RECORD
uarray-0.9.3.dist-info/WHEEL
uarray-0.9.3.dist-info/top_level.txt
uarray-0.9.3.dist-info/METADATA
uarray-0.9.3.dist-info/licenses/LICENSE
uarray/conftest.py
uarray/pytest.ini
uarray/_backend.py
uarray/_version.py
uarray/_uarray.pyi
uarray/__init__.py
uarray/_uarray.cpython-314-darwin.so
uarray/.coveragerc
uarray/_typing.pyi
uarray/py.typed
uarray/tests/example_helpers.py
uarray/tests/__init__.py
uarray/tests/test_uarray.py
